fret/__init__.py
fret/__main__.py
fret/app.py
fret/cli.py
fret/common.py
fret/util.py
fret/workspace.py
fret-0.3.5.dist-info/LICENSE
fret-0.3.5.dist-info/METADATA
fret-0.3.5.dist-info/WHEEL
fret-0.3.5.dist-info/entry_points.txt
fret-0.3.5.dist-info/top_level.txt
fret-0.3.5.dist-info/RECORD
