Metadata-Version: 2.1
Name: fret
Version: 0.3.5
Summary: Framework for Reproducible ExperimenTs.
Home-page: https://github.com/yxonic/fret
Author: yxonic
Author-email: yxonic@gmail.com
License: MIT
Platform: any
Classifier: Programming Language :: Python :: 3
Classifier: License :: OSI Approved :: MIT License
Classifier: Operating System :: OS Independent
Classifier: Intended Audience :: Science/Research
Requires-Python: >=3.4
Provides-Extra: test
Provides-Extra: doc
Provides-Extra: dev
